sendgrid_cli/__init__.py
sendgrid_cli/cli.py
sendgrid_cli-0.1.4.dist-info/entry_points.txt
sendgrid_cli-0.1.4.dist-info/WHEEL
sendgrid_cli-0.1.4.dist-info/METADATA
sendgrid_cli-0.1.4.dist-info/RECORD
