Metadata-Version: 2.1
Name: sendgrid-cli
Version: 0.1.4
Summary: 
Home-page: https://github.com/tddschn/sendgrid-cli
License: MIT
Keywords: email,sendgrid,CLI,utility
Author: Teddy Xinyuan Chen
Author-email: 45612704+tddschn@users.noreply.github.com
Requires-Python: >=3.10,<4.0
Classifier: License :: OSI Approved :: MIT License
Classifier: Programming Language :: Python :: 3
Classifier: Programming Language :: Python :: 3.10
Classifier: Topic :: Utilities
Requires-Dist: sendgrid (>=6.9.7,<7.0.0)
Project-URL: Bug Tracker, https://github.com/tddschn/sendgrid-cli/issues
Project-URL: Repository, https://github.com/tddschn/sendgrid-cli
